dictatorgenai/.DS_Store
dictatorgenai/__init__.py
dictatorgenai/agents/__init__.py
dictatorgenai/agents/assigned_general.py
dictatorgenai/agents/base_agent.py
dictatorgenai/agents/colonel_fragmenter.py
dictatorgenai/agents/dictator.py
dictatorgenai/agents/general.py
dictatorgenai/agents/information_officer.py
dictatorgenai/agents/legion_commander.py
dictatorgenai/agents/majordomo.py
dictatorgenai/agents/prompt.txt
dictatorgenai/agents/tool.py
dictatorgenai/command_chains/__init__.py
dictatorgenai/command_chains/command_chain.py
dictatorgenai/command_chains/default_command_chain.py
dictatorgenai/config/__init__.py
dictatorgenai/config/settings.py
dictatorgenai/conversations/__init__.py
dictatorgenai/conversations/base_conversation.py
dictatorgenai/conversations/group_chat.py
dictatorgenai/conversations/nested_chat.py
dictatorgenai/conversations/sequential_chat.py
dictatorgenai/conversations/two_agent_chat.py
dictatorgenai/events/__init__.py
dictatorgenai/events/base_event_manager.py
dictatorgenai/events/event.py
dictatorgenai/events/event_manager.py
dictatorgenai/examples/.chainlit/config.toml
dictatorgenai/examples/.chainlit/translations/bn.json
dictatorgenai/examples/.chainlit/translations/en-US.json
dictatorgenai/examples/.chainlit/translations/gu.json
dictatorgenai/examples/.chainlit/translations/he-IL.json
dictatorgenai/examples/.chainlit/translations/hi.json
dictatorgenai/examples/.chainlit/translations/kn.json
dictatorgenai/examples/.chainlit/translations/ml.json
dictatorgenai/examples/.chainlit/translations/mr.json
dictatorgenai/examples/.chainlit/translations/pt-BR.json
dictatorgenai/examples/.chainlit/translations/ta.json
dictatorgenai/examples/.chainlit/translations/te.json
dictatorgenai/examples/.chainlit/translations/zh-CN.json
dictatorgenai/examples/__init__.py
dictatorgenai/examples/chainlit.md
dictatorgenai/examples/dictator_chainlit_example.py
dictatorgenai/examples/medecine_regime.py
dictatorgenai/examples/server.py
dictatorgenai-0.1.2.dist-info/LICENSE
dictatorgenai-0.1.2.dist-info/METADATA
dictatorgenai-0.1.2.dist-info/WHEEL
dictatorgenai-0.1.2.dist-info/entry_points.txt
dictatorgenai-0.1.2.dist-info/RECORD
