Metadata-Version: 2.3
Name: dictatorgenai
Version: 0.1.2
Summary: An agentic Python library for multi-agents collaboration
License: MIT
Keywords: framework,ai,python,agentic,agent
Author: Jérémie Lenoir
Requires-Python: >=3.9,<3.12
Classifier: License :: OSI Approved :: MIT License
Classifier: Programming Language :: Python :: 3
Classifier: Programming Language :: Python :: 3.9
Classifier: Programming Language :: Python :: 3.10
Classifier: Programming Language :: Python :: 3.11
Provides-Extra: dev
Requires-Dist: chainlit (>=2.1.1,<3.0.0)
Requires-Dist: fastapi (==0.115.6)
Requires-Dist: openai (==1.58.1)
Requires-Dist: packaging (==23.2)
Requires-Dist: pydantic (==2.10.1)
Requires-Dist: pydantic-core (==2.27.1)
Project-URL: Homepage, https://github.com/smartlawyer-ai/dictatorgen
Project-URL: Repository, https://github.com/smartlawyer-ai/dictatorgen
